Workbook

Sheet README_Methodology
A1: Uber Find My Ride — TAM / SAM / SOM model (ILLUSTRATIVE, NOT A VALIDATED MARKET ESTIMATE)
A2: Prepared for a product-management assignment. Built 2026-10-16. Geography: India. Unit of analysis: annual ride-hailing pickup events (trips).
A4: WHY ILLUSTRATIVE
A5: No credible public source gives Uber India's annual trip count, the share of pickups with coordination problems, or the effectiveness of any fix. Public research supplies distance (11.6 bn km in 2025), a company-claimed Rapido ride count and low-confidence market-share estimates. Every other input is an editable assumption labelled 'Illustrative Assumption — Not Research Evidence'. Results show what the funnel looks like IF those assumptions hold.
A7: DEFINITIONS (distinct quantities — never interchangeable)
A8: TAM = total annual ride-hailing pickup events in India (all platforms) that could theoretically benefit from pickup-coordination improvement. Model!row 6.
A9: SAM = the part of TAM Uber can serve: Uber's share x eligible ride categories x rollout geography. Model!row 7.
A10: SOM = the part of SAM realistically obtainable within the time horizon (reach, Assumptions A6). Model!row 8.
A11: Because Find My Ride improves an existing service, four further quantities are modelled separately:
A12: (1) Addressable annual pickup events = SAM / SOM. (2) Events with relevant coordination problems = events x problem rate (Model rows 9-10).
A13: (3) Events the improvement could successfully address = problem events in SOM x effectiveness (row 11). (4) Incremental economic value (rows 12-15).
A15: 'TIM' — no use of the term was found in the project repository (searched .md and .gs files). TIM is not treated as TAM. If it appears in your earlier materials (e.g. Total Industry Market?), send the definition and it will be documented here.
... A27: 6. Results must not be quoted as Uber's market size or forecast.

Sheet Source_Registry
A1: ID | B1: Market input | C1: Value | D1: Unit | E1: Geography | F1: Reporting period | G1: Source URL | H1: Publication date | I1: Calculation / transformation applied | J1: Confidence | K1: Limitations | L1: Verification status | M1: Used in model?
A2: S1 | B2: Uber ride distance in India | C2: 11.6 | D2: billion km (total trip distance) | E2: India | F2: Calendar 2025 | G2: https://www.uber.com/en-IN/newsroom/how-india-ubered-in-2025-everyday-travel-extraordinary-scale | H2: January 2026 (per secondary coverage; exact date not verified) | I2: Used directly as A1; converted to trips by dividing by assumed km/trip (A2) | J2: Medium (company disclosure) | K2: Distance, not trips; includes all vehicle types; unclear whether pickup-approach km are excluded. Same page also states +26.5% vs 2024. | L2: Seen in web-search result summary 2026-10-16; page itself not opened (fetch blocked by network policy). | M2: Yes — A1
A3: S2 | B3: Uber ride distance in India (prior year) | C3: 9.2 | D3: billion km | E3: India | F3: Calendar 2024 | G3: https://www.storyboard18.com/how-it-works/india-logs-9-2-bn-kilometers-with-uber-in-2024-report-52740.htm | H3: Not verified | I3: Context only (11.6 / 9.2 = +26%) | J3: Medium (media report of company data) | K3: Secondary reporting. | L3: Seen in web-search result summary 2026-10-16; page itself not opened (fetch blocked by network policy). | M3: No (context)
A4: S3 | B4: Rapido rides, Q2 FY25 | C4: 207 | D4: million rides (quarter) | E4: India | F4: Q2 FY25 (Jul-Sep 2024) | G4: https://entrackr.com/news/rapido-claims-207-mn-rides-in-q2-fy25-with-25x-surge-in-gov-7579785 | H4: Not verified (2024) | I4: x4 to annualise = 828 million rides/yr (cross-check only) | J4: Low-Medium (company claim) | K4: Company-claimed; one quarter annualised ignores seasonality/growth; includes bike, auto and cab, and may include non-comparable products. | L4: Seen in web-search result summary 2026-10-16; page itself not opened (fetch blocked by network policy). | M4: Cross-check only — Model rows 18-20
A5: S4 | B5: Share of India ride-hailing rides: Rapido ~50%, Uber ~40% (all vehicle types); Uber ~45% of four-wheeler segment | C5: 0.4 | D5: share of rides (Uber, all vehicle types) | E5: India | F5: Not stated | G5: https://www.outlookbusiness.com/news/uber-pumps-3000-cr-into-india-arm-as-rapido-overtakes-in-total-rides | H5: Not verified | I5: Used as base A3 (0.40); cons 0.45 / opt 0.35 are illustrative | J5: Low (undated; underlying estimator unknown) | K5: Original estimator and period not confirmed; a different search result gave other shares. | L5: Seen in web-search result summary 2026-10-16; page itself not opened (fetch blocked by network policy). | M5: Yes — A3
A6: S5 | B6: Daily trips: Uber ~840k, Ola ~460k, Rapido ~320k | C6: 840000 | D6: trips/day (Uber) | E6: India | F6: Undated | G6: https://www.equentis.com/blog/?p=48722 | H6: Not verified | I6: NOT used. 840k x 365 = ~307 million/yr is inconsistent with S1/S3 and is likely dated or on a different basis. | J6: Low | K6: Undated; conflicts with other sources; shown to document the range of uncertainty. | L6: Seen in web-search result summary 2026-10-16; page itself not opened (fetch blocked by network policy). | M6: No (conflicting)
A7: S6 | B7: CCPA warning to Uber/Ola on complaints about cancellations, cancellation charges, surge pricing and long waits; National Consumer Helpline April grievances: Ola 2,482, Uber 770 | D7: n/a (qualitative; grievance counts) | E7: India | F7: 2022 | G7: https://www.moneylife.in/article/indian-regulator-warns-uber-ola-to-fix-customer-complaints-else-face-penal-action/67142.html | H7: 2022 (exact date not verified) | I7: None — qualitative context for 'problem exists' | J7: Medium (regulatory action reported by media) | K7: Grievance counts are not a trip-level incidence rate; no share attributed to pickup coordination. | L7: Seen in web-search result summary 2026-10-16; page itself not opened (fetch blocked by network policy). | M7: No (context)
A8: S7 | B8: LocalCircles survey: 71% of customers report driver cancellation issues | C8: 0.71 | D8: share of survey respondents | E8: India | F8: 2018 | G8: https://qz.com/india/1472888/indians-are-sick-of-ola-ubers-surge-pricing-cancellations | H8: 2018 | I8: NOT used as a rate: perception survey, not per-trip incidence | J8: Low for sizing | K8: Dated (2018); self-selected online panel; measures experience not trip share. | L8: Seen in web-search result summary 2026-10-16; page itself not opened (fetch blocked by network policy). | M8: No
A9: S8 | B9: Uber official airport driver pages (e.g. LAX): queue/staging lots, designated pickup zones, advice to contact rider on crowded pickups | D9: n/a (documented functionality) | E9: International (US/Canada airports) | F9: Pages current at retrieval | G9: https://www.uber.com/global/en/r/airports/lax/driver-information/ | H9: Not stated | I9: None — qualitative documentation; not India-specific | J9: Medium for documented process | K9: International; does not show performance or incidence. | L9: Seen in web-search result summary 2026-10-16; page itself not opened (fetch blocked by network policy). | M9: No (qualitative)

Sheet Assumptions
A1: Assumption inputs — edit blue cells only. Yellow = Illustrative Assumption, not research evidence.
A2: Scenario direction: Conservative = smallest opportunity, Optimistic = largest. Time horizon for SOM: 3 years (editable label, applied via A6).
A4: ID | B4: Parameter | C4: Unit | D4: Conservative | E4: Base | F4: Optimistic | G4: Evidence status | H4: Source / rationale (why needed)
A5: A1 | B5: Uber India annual trip distance | C5: billion km | D5: 11.6 | E5: 11.6 | F5: 11.6 | G5: Research-derived | H5: S1. Same in all scenarios.
A6: A2 | B6: Average rider trip distance (converts km to trips) | C6: km per trip | D6: 17.5 | E6: 12 | F6: 8 | G6: Illustrative Assumption — Not Research Evidence | H6: Uber publishes km, not trips. Needed to get a trip count. Conservative value 17.5 is chosen so Uber trips ~ 0.66 bn, matching the Rapido-based cross-check (rows 18-20); base/optimistic assume shorter trips.
A7: A3 | B7: Uber share of India ride-hailing trips (all platforms) | C7: share | D7: 0.45 | E7: 0.4 | F7: 0.35 | G7: Low-confidence secondary estimate (range illustrative) | H7: S4 base 0.40. Needed to scale Uber trips up to an all-platform TAM. Higher share = smaller TAM (conservative).
A8: A4 | B8: Share of Uber trips in ride categories eligible for the improvement | C8: share | D8: 0.5 | E8: 0.7 | F8: 0.9 | G8: Illustrative Assumption — Not Research Evidence | H8: Needed because rollout may exclude some categories (e.g. bike, shared, intercity). No public split used.
A9: A5 | B9: Share of eligible trips within initial rollout geography | C9: share | D9: 0.4 | E9: 0.6 | F9: 0.8 | G9: Illustrative Assumption — Not Research Evidence | H9: Needed because launch would not cover all cities. S1 only names top cities qualitatively.
A10: A6 | B10: Reach achieved within time horizon (3 years): share of SAM | C10: share | D10: 0.1 | E10: 0.25 | F10: 0.4 | G10: Illustrative Assumption — Not Research Evidence | H10: Needed to turn SAM (serviceable) into SOM (obtainable). No adoption evidence exists.
A11: A7 | B11: Coordination-problem rate: share of pickups with a relevant problem | C11: share of trips | D11: 0.05 | E11: 0.1 | F11: 0.15 | G11: Illustrative Assumption — Not Research Evidence | H11: No credible published trip-level rate found (S6/S7 are not rates). Deliberately NOT taken from the 26-person survey.
A12: A8 | B12: Effectiveness: share of problem events the improvement resolves | C12: share | D12: 0.2 | E12: 0.35 | F12: 0.5 | G12: Illustrative Assumption — Not Research Evidence | H12: Unknown until tested. Placeholder to show sensitivity.
A13: A9 | B13: Share of resolved problem events that would otherwise have lost the trip (cancel/no-show) | C13: share | D13: 0.2 | E13: 0.3 | F13: 0.4 | G13: Illustrative Assumption — Not Research Evidence | H13: Needed to link coordination problems to lost revenue. Not measured.
A14: A10 | B14: Average fare per trip | C14: INR | D14: 200 | E14: 250 | F14: 300 | G14: Illustrative Assumption — Not Research Evidence | H14: No fare source gathered; editable placeholder.
A15: A11 | B15: Platform take rate on fare | C15: share | D15: 0.15 | E15: 0.2 | F15: 0.25 | G15: Illustrative Assumption — Not Research Evidence | H15: No India take-rate source gathered; editable placeholder.
A16: A12 | B16: Rider minutes saved per resolved problem event | C16: minutes | D16: 3 | E16: 5 | F16: 8 | G16: Illustrative Assumption — Not Research Evidence | H16: Placeholder for rider-side benefit (hours, not monetised).
... A18: R2 | B18: Rapido share of India ride-hailing rides (cross-check) | C18: share | D18: 0.5 | E18: 0.5 | F18: 0.5 | G18: Low-confidence secondary estimate (range illustrative) | H18: S4.

Sheet Model
A1: TAM / SAM / SOM and incremental-value model — all cells are formulas on the Assumptions sheet (annual, India)
A4: Row | B4: Quantity | C4: Unit | D4: Conservative | E4: Base | F4: Optimistic | G4: Formula logic
A5: 5 | B5: Uber India annual trips (derived from km) | C5: million trips | D5: =Assumptions!D5*1000/Assumptions!D6 -> 662.85714 | E5: =Assumptions!E5*1000/Assumptions!E6 -> 966.66667 | F5: =Assumptions!F5*1000/Assumptions!F6 -> 1450 | G5: A1 bn km x 1000 / km per trip (A2)
A6: 6 | B6: TAM — all-platform India ride-hailing pickup events | C6: million events | D6: =D5/Assumptions!D7 -> 1473.0159 | E6: =E5/Assumptions!E7 -> 2416.6667 | F6: =F5/Assumptions!F7 -> 4142.8571 | G6: Uber trips / Uber share (A3)
A7: 7 | B7: SAM — Uber-serviceable pickup events | C7: million events | D7: =D6*Assumptions!D7*Assumptions!D8*Assumptions!D9 -> 132.57143 | E7: =E6*Assumptions!E7*Assumptions!E8*Assumptions!E9 -> 406 | F7: =F6*Assumptions!F7*Assumptions!F8*Assumptions!F9 -> 1044 | G7: TAM x Uber share x eligible categories x rollout geography
A8: 8 | B8: SOM — obtainable within horizon | C8: million events | D8: =D7*Assumptions!D10 -> 13.257143 | E8: =E7*Assumptions!E10 -> 101.5 | F8: =F7*Assumptions!F10 -> 417.6 | G8: SAM x reach (A6)
A9: 9 | B9: Events with coordination problems — within SAM | C9: million events | D9: =D7*Assumptions!D11 -> 6.6285714 | E9: =E7*Assumptions!E11 -> 40.6 | F9: =F7*Assumptions!F11 -> 156.6 | G9: SAM x problem rate (A7)
A10: 10 | B10: Events with coordination problems — within SOM | C10: million events | D10: =D8*Assumptions!D11 -> 0.66285714 | E10: =E8*Assumptions!E11 -> 10.15 | F10: =F8*Assumptions!F11 -> 62.64 | G10: SOM x problem rate (A7)
A11: 11 | B11: Events the improvement could successfully address (SOM) | C11: million events | D11: =D10*Assumptions!D12 -> 0.13257143 | E11: =E10*Assumptions!E12 -> 3.5525 | F11: =F10*Assumptions!F12 -> 31.32 | G11: Problem events in SOM x effectiveness (A8)
A12: 12 | B12: Trips retained (would otherwise be lost) | C12: million trips | D12: =D11*Assumptions!D13 -> 0.026514286 | E12: =E11*Assumptions!E13 -> 1.06575 | F12: =F11*Assumptions!F13 -> 12.528 | G12: Addressed events x A9
A13: 13 | B13: Incremental platform revenue | C13: INR million | D13: =D12*Assumptions!D14*Assumptions!D15 -> 0.79542857 | E13: =E12*Assumptions!E14*Assumptions!E15 -> 53.2875 | F13: =F12*Assumptions!F14*Assumptions!F15 -> 939.6 | G13: Retained trips x fare x take rate
A14: 14 | B14: Incremental platform revenue | C14: INR crore | D14: =D13/10 -> 0.079542857 | E14: =E13/10 -> 5.32875 | F14: =F13/10 -> 93.96 | G14: 1 crore = 10 million
A15: 15 | B15: Rider time saved | C15: million hours | D15: =D11*Assumptions!D16/60 -> 0.0066285714 | E15: =E11*Assumptions!E16/60 -> 0.29604167 | F15: =F11*Assumptions!F16/60 -> 4.176 | G15: Addressed events x minutes / 60
A17: Cross-check: is the km-to-trips conversion plausible? (not used in the funnel)
A18: 18 | B18: Rapido rides, annualised (Q2 FY25 x 4) | C18: million rides | D18: =Assumptions!D17*4 -> 828 | E18: =Assumptions!E17*4 -> 828 | F18: =Assumptions!F17*4 -> 828 | G18: S3 x 4; ignores seasonality; company claim
A19: 19 | B19: Implied Uber trips if Uber/Rapido ride ratio = A3/R2 | C19: million trips | D19: =D18*Assumptions!D7/Assumptions!D18 -> 745.2 | E19: =E18*Assumptions!E7/Assumptions!E18 -> 662.4 | F19: =F18*Assumptions!F7/Assumptions!F18 -> 579.6 | G19: Rapido annualised x (Uber share / Rapido share)
A20: 20 | B20: Model Uber trips vs cross-check (ratio) | C20: x | D20: =D5/D19 -> 0.88950234 | E20: =E5/E19 -> 1.4593398 | F20: =F5/F19 -> 2.5017253 | G20: 1.0 = agreement; far from 1.0 = conversion A2 needs work

Sheet Sensitivity
A1: Sensitivity around the BASE case — incremental platform revenue (INR crore, annual, within SOM)
A2: Table 1: two-way grid. Rows = coordination-problem rate (A7); columns = effectiveness (A8). All other inputs at Base.
A4: Problem rate \ Effectiveness | B4: 0.1 | C4: 0.2 | D4: 0.35 | E4: 0.5 | F4: 0.7
A5: 0.02 | B5: =Model!$E$8*$A5*B$4*Assumptions!$E$13*Assumptions!$E$14*Assumptions!$E$15/10 -> 0.3045 | C5: =Model!$E$8*$A5*C$4*Assumptions!$E$13*Assumptions!$E$14*Assumptions!$E$15/10 -> 0.609 | D5: =Model!$E$8*$A5*D$4*Assumptions!$E$13*Assumptions!$E$14*Assumptions!$E$15/10 -> 1.06575 | E5: =Model!$E$8*$A5*E$4*Assumptions!$E$13*Assumptions!$E$14*Assumptions!$E$15/10 -> 1.5225 | F5: =Model!$E$8*$A5*F$4*Assumptions!$E$13*Assumptions!$E$14*Assumptions!$E$15/10 -> 2.1315
A6: 0.05 | B6: =Model!$E$8*$A6*B$4*Assumptions!$E$13*Assumptions!$E$14*Assumptions!$E$15/10 -> 0.76125 | C6: =Model!$E$8*$A6*C$4*Assumptions!$E$13*Assumptions!$E$14*Assumptions!$E$15/10 -> 1.5225 | D6: =Model!$E$8*$A6*D$4*Assumptions!$E$13*Assumptions!$E$14*Assumptions!$E$15/10 -> 2.664375 | E6: =Model!$E$8*$A6*E$4*Assumptions!$E$13*Assumptions!$E$14*Assumptions!$E$15/10 -> 3.80625 | F6: =Model!$E$8*$A6*F$4*Assumptions!$E$13*Assumptions!$E$14*Assumptions!$E$15/10 -> 5.32875
A7: 0.1 | B7: =Model!$E$8*$A7*B$4*Assumptions!$E$13*Assumptions!$E$14*Assumptions!$E$15/10 -> 1.5225 | C7: =Model!$E$8*$A7*C$4*Assumptions!$E$13*Assumptions!$E$14*Assumptions!$E$15/10 -> 3.045 | D7: =Model!$E$8*$A7*D$4*Assumptions!$E$13*Assumptions!$E$14*Assumptions!$E$15/10 -> 5.32875 | E7: =Model!$E$8*$A7*E$4*Assumptions!$E$13*Assumptions!$E$14*Assumptions!$E$15/10 -> 7.6125 | F7: =Model!$E$8*$A7*F$4*Assumptions!$E$13*Assumptions!$E$14*Assumptions!$E$15/10 -> 10.6575
A8: 0.15 | B8: =Model!$E$8*$A8*B$4*Assumptions!$E$13*Assumptions!$E$14*Assumptions!$E$15/10 -> 2.28375 | C8: =Model!$E$8*$A8*C$4*Assumptions!$E$13*Assumptions!$E$14*Assumptions!$E$15/10 -> 4.5675 | D8: =Model!$E$8*$A8*D$4*Assumptions!$E$13*Assumptions!$E$14*Assumptions!$E$15/10 -> 7.993125 | E8: =Model!$E$8*$A8*E$4*Assumptions!$E$13*Assumptions!$E$14*Assumptions!$E$15/10 -> 11.41875 | F8: =Model!$E$8*$A8*F$4*Assumptions!$E$13*Assumptions!$E$14*Assumptions!$E$15/10 -> 15.98625
A9: 0.2 | B9: =Model!$E$8*$A9*B$4*Assumptions!$E$13*Assumptions!$E$14*Assumptions!$E$15/10 -> 3.045 | C9: =Model!$E$8*$A9*C$4*Assumptions!$E$13*Assumptions!$E$14*Assumptions!$E$15/10 -> 6.09 | D9: =Model!$E$8*$A9*D$4*Assumptions!$E$13*Assumptions!$E$14*Assumptions!$E$15/10 -> 10.6575 | E9: =Model!$E$8*$A9*E$4*Assumptions!$E$13*Assumptions!$E$14*Assumptions!$E$15/10 -> 15.225 | F9: =Model!$E$8*$A9*F$4*Assumptions!$E$13*Assumptions!$E$14*Assumptions!$E$15/10 -> 21.315
A12: Table 2: one-way swing. Each row swaps ONE input to its Conservative / Optimistic value; all others at Base (INR crore).
A13: Input swapped | B13: Conservative value -> result | C13: Base result | D13: Optimistic value -> result | E13: Swing (opt - cons) | F13: Note
A14: A2 km per trip | B14: =Model!$E$14*Assumptions!$E$6/Assumptions!$D$6 -> 3.654 | C14: =Model!$E$14 -> 5.32875 | D14: =Model!$E$14*Assumptions!$E$6/Assumptions!$F$6 -> 7.993125 | E14: =D14-B14 -> 4.339125 | F14: Trips scale with 1 / km per trip
A15: A4 eligible categories | B15: =Model!$E$14*Assumptions!$D$8/Assumptions!$E$8 -> 3.80625 | C15: =Model!$E$14 -> 5.32875 | D15: =Model!$E$14*Assumptions!$F$8/Assumptions!$E$8 -> 6.85125 | E15: =D15-B15 -> 3.045 | F15: Linear (multiplicative) input
A16: A5 rollout geography | B16: =Model!$E$14*Assumptions!$D$9/Assumptions!$E$9 -> 3.5525 | C16: =Model!$E$14 -> 5.32875 | D16: =Model!$E$14*Assumptions!$F$9/Assumptions!$E$9 -> 7.105 | E16: =D16-B16 -> 3.5525 | F16: Linear (multiplicative) input
A17: A6 reach in horizon | B17: =Model!$E$14*Assumptions!$D$10/Assumptions!$E$10 -> 2.1315 | C17: =Model!$E$14 -> 5.32875 | D17: =Model!$E$14*Assumptions!$F$10/Assumptions!$E$10 -> 8.526 | E17: =D17-B17 -> 6.3945 | F17: Linear (multiplicative) input
A18: A7 problem rate | B18: =Model!$E$14*Assumptions!$D$11/Assumptions!$E$11 -> 2.664375 | C18: =Model!$E$14 -> 5.32875 | D18: =Model!$E$14*Assumptions!$F$11/Assumptions!$E$11 -> 7.993125 | E18: =D18-B18 -> 5.32875 | F18: Linear (multiplicative) input
A19: A8 effectiveness | B19: =Model!$E$14*Assumptions!$D$12/Assumptions!$E$12 -> 3.045 | C19: =Model!$E$14 -> 5.32875 | D19: =Model!$E$14*Assumptions!$F$12/Assumptions!$E$12 -> 7.6125 | E19: =D19-B19 -> 4.5675 | F19: Linear (multiplicative) input
A20: A9 trips otherwise lost | B20: =Model!$E$14*Assumptions!$D$13/Assumptions!$E$13 -> 3.5525 | C20: =Model!$E$14 -> 5.32875 | D20: =Model!$E$14*Assumptions!$F$13/Assumptions!$E$13 -> 7.105 | E20: =D20-B20 -> 3.5525 | F20: Linear (multiplicative) input
A21: A10 average fare | B21: =Model!$E$14*Assumptions!$D$14/Assumptions!$E$14 -> 4.263 | C21: =Model!$E$14 -> 5.32875 | D21: =Model!$E$14*Assumptions!$F$14/Assumptions!$E$14 -> 6.3945 | E21: =D21-B21 -> 2.1315 | F21: Linear (multiplicative) input
A22: A11 take rate | B22: =Model!$E$14*Assumptions!$D$15/Assumptions!$E$15 -> 3.9965625 | C22: =Model!$E$14 -> 5.32875 | D22: =Model!$E$14*Assumptions!$F$15/Assumptions!$E$15 -> 6.6609375 | E22: =D22-B22 -> 2.664375 | F22: Linear (multiplicative) input
A23: A3 Uber share | B23: =Model!$E$14 -> 5.32875 | C23: =Model!$E$14 -> 5.32875 | D23: =Model!$E$14 -> 5.32875 | E23: =D23-B23 -> 0 | F23: No effect on SAM/SOM/value (share cancels); affects TAM only
A25: All inputs Conservative | B25: =Model!D14 -> 0.079542857
A26: All inputs Optimistic | B26: =Model!F14 -> 93.96
A27: Reading: results are products of uncertain inputs; the range between all-conservative and all-optimistic spans orders of magnitude, so only the structure of the funnel, not the level, is informative.
